<?xml version="1.0" encoding="utf-8"?>
<ClassBase xmlns:xsi="http://www.w3.org/2001/XMLSchema-instance"
           xmlns:xsd="http://www.w3.org/2001/XMLSchema">
	<Guild>0</Guild>
	<Class>1</Class>
	<Coin>0</Coin>
	<PosX>2096</PosX>
	<PosY>2096</PosY>
	<Level>0</Level>
	<Defense>4</Defense>
	<Attack>6</Attack>
	<Merchant>0</Merchant>
	<MobSpeed>82</MobSpeed>
	<Direction>4</Direction>
	<ChaosRate>5</ChaosRate>
	<MaxHP>60</MaxHP>
	<MaxMP>65</MaxMP>
	<CurHP>60</CurHP>
	<CurMP>65</CurMP>
	<BaseStatus>5,10,5,5</BaseStatus>
	<Special>0,0,0,0</Special>
	<LearnedSkill>0</LearnedSkill>
	<Magic>0</Magic>
	<ScoreBonus>0</ScoreBonus>
	<SpecialBonus>0</SpecialBonus>
	<SkillBonus>0</SkillBonus>
	<Critikal>255</Critikal>
	<SaveMana>255</SaveMana>
	<GuildLevel>0</GuildLevel>
	<RegenHP>0</RegenHP>
	<RegenMP>0</RegenMP>
	<SkillBar>255,255,255,255</SkillBar>
	<Resist>245,245,245,245</Resist>
	<Face>11,0,0,0,0,0,0</Face>
	<Helmet>1253,0,0,0,0,0,0</Helmet>
	<Armor>1265,0,0,0,0,0,0</Armor>
	<Pant>1277,0,0,0,0,0,0</Pant>
	<Glove>1289,0,0,0,0,0,0</Glove>
	<Boot>1301,0,0,0,0,0,0</Boot>
	<Weapon>861,0,0,0,0,0,0</Weapon>
	<Shield>0,0,0,0,0,0,0</Shield>
	<Ring> 0,0,0,0,0,0,0</Ring>
	<Amulet>0,0,0,0,0,0,0</Amulet>
	<Orb>0,0,0,0,0,0,0</Orb>
	<Stone>0,0,0,0,0,0,0</Stone>
	<Traje>0,0,0,0,0,0,0</Traje>
	<Pixie>0,0,0,0,0,0,0</Pixie>
	<Mount>0,0,0,0,0,0,0</Mount>
	<Mantle>0,0,0,0,0,0,0</Mantle>
</ClassBase>